datasette_embeddings/__init__.py
datasette_embeddings/templates/embeddings_semantic_search.html
datasette_embeddings-0.1a3.dist-info/LICENSE
datasette_embeddings-0.1a3.dist-info/METADATA
datasette_embeddings-0.1a3.dist-info/WHEEL
datasette_embeddings-0.1a3.dist-info/entry_points.txt
datasette_embeddings-0.1a3.dist-info/top_level.txt
datasette_embeddings-0.1a3.dist-info/RECORD
