Metadata-Version: 2.1
Name: datasette-embeddings
Version: 0.1a3
Summary: Store and query embedding vectors in Datasette tables
Author: Datasette
License: Apache-2.0
Project-URL: Homepage, https://github.com/datasette/datasette-embeddings
Project-URL: Changelog, https://github.com/datasette/datasette-embeddings/releases
Project-URL: Issues, https://github.com/datasette/datasette-embeddings/issues
Project-URL: CI, https://github.com/datasette/datasette-embeddings/actions
Classifier: Framework :: Datasette
Classifier: License :: OSI Approved :: Apache Software License
Requires-Python: >=3.8
License-File: LICENSE
Requires-Dist: datasette
Requires-Dist: datasette-enrichments
Requires-Dist: sqlite-utils
Requires-Dist: httpx
Provides-Extra: test
Requires-Dist: pytest ; extra == 'test'
Requires-Dist: pytest-asyncio ; extra == 'test'
Requires-Dist: pytest-recording ; extra == 'test'
Requires-Dist: datasette-test ; extra == 'test'
